datachop.py
datachop-1.0.0.dist-info/licenses/LICENSE
datachop-1.0.0.dist-info/METADATA
datachop-1.0.0.dist-info/WHEEL
datachop-1.0.0.dist-info/top_level.txt
datachop-1.0.0.dist-info/RECORD
