Metadata-Version: 2.4
Name: datachop
Version: 1.0.0
Summary: The Ultimate Slicing Module for various data types and files.
Home-page: https://github.com/mallikmusaddiq1/datachop
Author: Mallik Mohammad Musaddiq
Author-email: Mallik Mohammad Musaddiq <mallikmusaddiq1@gmail.com>
Project-URL: Homepage, https://github.com/mallikmusaddiq1/datachop
Project-URL: Repository, https://github.com/mallikmusaddiq1/datachop
Keywords: slicing,data,processing,files,images,video,audio
Classifier: Programming Language :: Python :: 3
Classifier: License :: OSI Approved :: MIT License
Classifier: Operating System :: OS Independent
Classifier: Development Status :: 5 - Production/Stable
Classifier: Intended Audience :: Developers
Classifier: Topic :: Software Development :: Libraries :: Python Modules
Classifier: Topic :: Utilities
Requires-Python: >=3.8
License-File: LICENSE
Requires-Dist: regex>=2024.5.15
Requires-Dist: charset-normalizer>=3.3.2
Requires-Dist: Pillow>=10.3.0
Requires-Dist: moviepy>=1.0.3
Requires-Dist: ffmpeg-python>=0.2.0
Requires-Dist: PyPDF2>=3.0.1
Requires-Dist: python-docx>=1.1.0
Requires-Dist: odfpy>=1.4.1
Requires-Dist: pydub>=0.25.1
Requires-Dist: numpy>=1.26.4
Requires-Dist: tqdm>=4.66.4
Requires-Dist: redis>=5.0.4
Provides-Extra: full
Requires-Dist: pydub; extra == "full"
Requires-Dist: pillow; extra == "full"
Requires-Dist: moviepy; extra == "full"
Requires-Dist: ffmpeg-python; extra == "full"
Requires-Dist: pypdf2; extra == "full"
Requires-Dist: python-docx; extra == "full"
Requires-Dist: odfpy; extra == "full"
Requires-Dist: numpy; extra == "full"
Requires-Dist: tqdm; extra == "full"
Requires-Dist: redis; extra == "full"
Dynamic: author
Dynamic: home-page
Dynamic: license-file
Dynamic: requires-python
